curve_method/__init__.py
curve_method/evaluation.py
curve_method/plotting.py
curve_method/validation.py
curve_method/variance.py
curve_method/__pycache__/__init__.cpython-37.pyc
curve_method/__pycache__/evaluation.cpython-37.pyc
curve_method/__pycache__/plotting.cpython-37.pyc
curve_method/__pycache__/validation.cpython-37.pyc
curve_method/__pycache__/variance.cpython-37.pyc
curve_method-0.2.2.dist-info/LICENSE
curve_method-0.2.2.dist-info/METADATA
curve_method-0.2.2.dist-info/WHEEL
curve_method-0.2.2.dist-info/top_level.txt
curve_method-0.2.2.dist-info/RECORD
