Metadata-Version: 2.1
Name: curve-method
Version: 0.2.2
Summary: A quantitative approach to select the optimal number of clusters in a dataset.
Home-page: https://github.com/alexjfreund/curve_method
Author: Alex Freund
Author-email: alexjfreund@gmail.com
License: MIT
Download-URL: https://github.com/alexjfreund/curve_method/archive/v0.2.2.tar.gz
Platform: UNKNOWN
Classifier: Programming Language :: Python :: 3
Classifier: Programming Language :: Python :: 3.7
Classifier: Programming Language :: Python :: 3.8
Requires-Dist: numpy
Requires-Dist: matplotlib
Requires-Dist: scikit-learn
